molab/__init__.py
molab/configure.py
molab/controllers.py
molab/courses.py
molab/deploy.py
molab/destroy.py
molab/helpers.py
molab/labs.py
molab/tools.py
molab/template_files/MorpheusImage.png
molab/template_files/admin_class_config.json
molab/template_files/admin_class_tf_vars.json
molab/template_files/automation_class_config.json
molab/template_files/automation_class_tf_vars.json
molab/template_files/git_auth_type_pat.json
molab/template_files/install_class_config.json
molab/template_files/install_class_tf_vars.json
molab/template_files/instance_provisioning_payload.json
molab/template_files/manual_option_list_aws_regions.json
molab/template_files/platform_setup.json
molab/template_files/provisioning_payload.json
molab/template_files/troubleshooting_class_config.json
molab/template_files/troubleshooting_class_tf_vars.json
molab-0.7.12.dist-info/METADATA
molab-0.7.12.dist-info/WHEEL
molab-0.7.12.dist-info/top_level.txt
molab-0.7.12.dist-info/RECORD
