Metadata-Version: 2.1
Name: molab
Version: 0.7.12
Summary: molab is a python package for configuring Morpheus training lab environments.
Home-page: https://gitlab.com/morpheus_training/molab
Author: Sean Jabro
Author-email: sean.jabro@outlook.com
License: MIT
Classifier: Development Status :: 4 - Beta
Classifier: License :: OSI Approved :: MIT License
Classifier: Programming Language :: Python
Classifier: Programming Language :: Python :: 3.9
Requires-Python: >=3.8
Requires-Dist: urllib3
Requires-Dist: requests
Requires-Dist: requests-futures
Requires-Dist: loguru
Requires-Dist: morpheus-cypher
Requires-Dist: importlib-resources
Requires-Dist: boto3
